{
    "title": "克罗地亚个人资料 - 时间表",
    "link": "https://www.bbc.co.uk/news/world-europe-17217954",
    "content": [
        {
            "type": "image",
            "content": "https://ichef.bbci.co.uk/ace/standard/976/cpsprodpb/C315/production/_127814994_gettyimages-499397744.jpg"
        },
        {
            "type": "paragraph",
            "content": "克罗地亚首都萨格勒布的鸟瞰图"
        },
        {
            "type": "paragraph",
            "content": "关键事件的年表："
        },
        {
            "type": "paragraph",
            "content": "1918年 - 克罗地亚国民议会投票，将新的塞族，克罗地亚和斯洛文斯王国加入奥匈帝国的解散。"
        },
        {
            "type": "paragraph",
            "content": "1921年 - 统一的宪法废除了克罗地亚的自主权。克罗地亚主要的农民党为其恢复而开展运动。"
        },
        {
            "type": "paragraph",
            "content": "1929年 - 王国被更名为南斯拉夫，政府制度在皇家独裁统治下进一步集中。"
        },
        {
            "type": "paragraph",
            "content": "1939年 - 克罗地亚农民党谈判了对克罗地亚自治的部分恢复。"
        },
        {
            "type": "paragraph",
            "content": "1941年 - 纳粹德国入侵。形成了一个“大克罗地亚”，还包括大部分波斯尼亚和塞尔维亚西部。法西斯木偶政府安装在帕维尔（Ante Pavelic）下。"
        },
        {
            "type": "paragraph",
            "content": "该政权对塞尔维亚人和犹太人寻求建立一个天主教徒共和国，对塞尔维亚人和犹太人进行残酷行动。成千上万的人丧生。"
        },
        {
            "type": "paragraph",
            "content": "1945年 - 在铁托（Tito）领导下的共产党游击队的激烈抵抗运动之后，克罗地亚成为南斯拉夫社会主义联盟的六个组成共和国之一。"
        },
        {
            "type": "paragraph",
            "content": "1967年 - 克罗地亚作家要求更大的语言自主权，促使政治，经济和文化自由化运动。"
        },
        {
            "type": "paragraph",
            "content": "1971年 - 抗议者要求在称为“克罗地亚春天”的运动中更大的自主权。南斯拉夫当局谴责它是民族主义，逮捕学生和活动家，并清除克罗地亚共产党。"
        },
        {
            "type": "paragraph",
            "content": "1974年 - 新的南斯拉夫联邦宪法符合克罗地亚自治的一些要求。"
        },
        {
            "type": "paragraph",
            "content": "1980年 - 铁托去世。南斯拉夫的缓慢瓦解始于个人共和国主张他们对独立的渴望。"
        },
        {
            "type": "paragraph",
            "content": "1989年 - 东欧共产主义的崩溃导致通过民族主义计划对政党的支持提高。"
        },
        {
            "type": "paragraph",
            "content": "1990年 - 克罗地亚首次自由选举超过50年。共产党人输给了由弗朗乔·图杰曼（Franjo Tudjman）领导的保守派民族主义者。"
        },
        {
            "type": "paragraph",
            "content": "1991年 - 克罗地亚宣布其独立性。在南斯拉夫军队的帮助下，该国东部的克罗地亚塞族人驱逐了克罗地亚人。到今年年底，近三分之一的克罗地亚领土受到塞尔维亚卫生的控制。"
        },
        {
            "type": "paragraph",
            "content": "1992年 - 联合国在克罗地亚设立了四个保护区，有14,000名联合国部队将克罗地亚人和塞族人分开。克罗地亚还参与了波斯尼亚 - 黑塞哥维那的战争（1992-5），支持波斯尼亚克罗地亚人抵抗波斯尼亚塞族人，然后对波斯尼亚人（穆斯林）。弗朗乔·图杰曼（Franjo Tudjman）当选克罗地亚总统。"
        },
        {
            "type": "paragraph",
            "content": "1995年 - 克罗地亚部队夺回了联合国创建的四个地区中的三个。克罗地亚塞族人逃往波斯尼亚和塞尔维亚。图杰曼（Tudjman）是代顿和平协定（Dayton Peace Accort）的签署国之一，结束了波斯尼亚 - 黑塞哥维那的战争。"
        },
        {
            "type": "paragraph",
            "content": "1996年 - 克罗地亚恢复了与南斯拉夫的外交关系。克罗地亚加入欧洲议会。"
        },
        {
            "type": "paragraph",
            "content": "1997年 - 图杰曼（Tudjman）再次当选为总统。欧盟决定不邀请克罗地亚开始会员谈话，批评塔迪曼政权的专制倾向。"
        },
        {
            "type": "paragraph",
            "content": "1998年 - 克罗地亚恢复了对第四联合国斯拉沃尼亚东部地区的控制权。"
        },
        {
            "type": "paragraph",
            "content": "1999年 - 弗兰霍·图杰曼（Franjo Tudjman）去世。"
        },
        {
            "type": "paragraph",
            "content": "2000年1月 - 议会选举参见Franjo Tudjman的HDZ政党，被社会民主党和社会自由主义者联盟击败，而Ivica Racan成为新任总理。"
        },
        {
            "type": "paragraph",
            "content": "2000年2月 - 克罗地亚人民党的Stjepan Mesic当选为总统。"
        },
        {
            "type": "paragraph",
            "content": "2001年2月/3月 - 经过两周的奔跑，民族主义者在他的支持下组织了示威活动，米尔科·诺拉克将军（1991年被控杀害塞尔维亚平民），以他的身份不被引渡到国际上的克罗地亚法院海牙战争犯罪法庭。"
        },
        {
            "type": "paragraph",
            "content": "2001年7月 - 拉甘总理在民族主义者提出的议会中幸存下来的信任投票，反对他决定遵守海牙法庭提出的，要求其引渡阿里扬·阿德米将军和安特·戈多维纳。阿德米将军自愿出现在法庭面前。Gotovina将军躲藏起来。"
        },
        {
            "type": "paragraph",
            "content": "2001年9月 - 海牙法庭起诉前南斯拉夫总统斯洛博丹·米洛舍维奇（Slobodan Milosevic）在1990年代初期在克罗地亚战争中涉及战争罪和危害人类罪。"
        },
        {
            "type": "paragraph",
            "content": "2001年12月 - 南斯拉夫返回艺术作品，包括正统的偶像，在10年前Vukovar倒塌后被抢劫。"
        },
        {
            "type": "paragraph",
            "content": "2002APRIL-外交大臣托尼诺·皮卡拉（Tonino Picula）访问了贝尔格莱德（Belgrade）与南斯拉夫（Sothav）的对手进行会谈，这是自独立以来的第一次访问。"
        },
        {
            "type": "paragraph",
            "content": "2002年7月-PM Racan辞职，因为联盟内的内斗瘫痪了经济改革。MESIC总统要求他组建一个新政府。"
        },
        {
            "type": "paragraph",
            "content": "2002年9月 - 在民族主义者的压力下，政府拒绝移交退休的Janko Bobetko将军，后者被海牙法庭指控战争罪。提到了健康理由。"
        },
        {
            "type": "paragraph",
            "content": "2003年2月 - 克罗地亚提交欧盟会员的正式申请。"
        },
        {
            "type": "paragraph",
            "content": "2003年3月 - 米尔科·诺拉克（Mirko Norac）将军被许多克罗地亚人视为战争英雄，在1991年因杀害数十名塞族平民而被判处12年徒刑。"
        },
        {
            "type": "paragraph",
            "content": "2003年4月 -  Bobetko将军的去世结束了他引渡到海牙的争议。"
        },
        {
            "type": "paragraph",
            "content": "2003年10月 - 克罗地亚议会投票通过亚得利亚促使斯洛文尼亚的异议建立生态区。"
        },
        {
            "type": "paragraph",
            "content": "2003年12月 - 右翼克罗地亚民主联盟（HDZ）的伊沃·萨纳德（Ivo Sanader）成为少数派政府的总理，因为他的政党上个月在选举中取得了成功。"
        },
        {
            "type": "paragraph",
            "content": "2004年6月 - 战时克罗地亚塞族领导人米兰·巴比奇（Milan Babic）被海牙法庭判处13年徒刑，因为他在自称为1990年代初期的自称为Krajina Serb Republic的战争罪中针对非serbs的战争罪。"
        },
        {
            "type": "paragraph",
            "content": "2004年12月 - 欧盟同意于2005年3月与克罗地亚进行谈判。"
        },
        {
            "type": "paragraph",
            "content": "2005年1月 - 现任总统Stjepan Mesic赢得了第二学期。"
        },
        {
            "type": "paragraph",
            "content": "2005年3月 - 欧盟延误了关于克罗地亚会员资格的谈判，因为未能逮捕安特·戈多维纳将军，后者因战争罪名而被海牙法庭通缉。"
        },
        {
            "type": "paragraph",
            "content": "2005年10月 - 欧盟加入对话的绿灯即使Gen Gen Gen Den仍然很整个。"
        },
        {
            "type": "paragraph",
            "content": "克罗地亚要求在斯洛文尼亚议会宣布亚得里亚海的生态区之后，要求国际调解，以保护和使用海床的权利。"
        },
        {
            "type": "paragraph",
            "content": "2005年12月 - 海牙法庭因战争罪指控而寻求的逃离克罗地亚将军安特·戈多维纳（Ante Gotovina）在西班牙被捕。"
        },
        {
            "type": "paragraph",
            "content": "2006年11月 - 欧洲委员会发布报告批评克罗地亚对欧盟成员的进展。它说，需要做更多的事情来解决非恐怖的腐败和不宽容。"
        },
        {
            "type": "paragraph",
            "content": "2007年10月 - 工作始于沿海peljesac桥梁，这将使驾车者能够从波斯尼亚受到批评。"
        },
        {
            "type": "paragraph",
            "content": "2007年11月 - 议会选举。统治的克罗地亚民主联盟（HDZ）赢得了最多的席位，但需要联盟伙伴才能确保多数席位。"
        },
        {
            "type": "paragraph",
            "content": "2008年1月 - 议会批准总理伊沃·萨纳德（Ivo Sanader）的新HDZ领导的联合政府。包括首先在关键位置：副PM Slobodan Uzelac。"
        },
        {
            "type": "paragraph",
            "content": "2008年3月 - 克罗地亚前传教士Ante Gotovina，Ivan Cermak和Mladen Markac在Hague War Crimes Crimes仲裁庭接受审判，罪名是1990年代杀害克罗地亚塞族人。他们否认指控。"
        },
        {
            "type": "paragraph",
            "content": "2008APRIL-布加勒斯特的北约峰会邀请克罗地亚加入联盟。"
        },
        {
            "type": "paragraph",
            "content": "2008年10月 - 政府在与黑手党有关的一系列杀戮之后宣布重大反对有组织犯罪的动力。"
        },
        {
            "type": "paragraph",
            "content": "2009年2月 - 斯洛文尼亚威胁要阻止邻近的克罗地亚加入欧盟，持续争议。"
        },
        {
            "type": "paragraph",
            "content": "2009APRIL-克罗地亚加入北约。"
        },
        {
            "type": "paragraph",
            "content": "2009年7月 - 出乎意料的举动，总理伊沃·萨纳德（Ivo Sanader）宣布他将辞职并退出积极的政治。议会批准萨纳德先生的副手贾德兰卡·科索尔（Jadranka Kosor）担任总理。"
        },
        {
            "type": "paragraph",
            "content": "2009年11月 - 克罗地亚欧盟会员谈判的斯洛文尼亚举重街区，两国签署协议允许国际调解人解决其边境纠纷。克罗地亚欧盟会员会谈简历。"
        },
        {
            "type": "paragraph",
            "content": "2010年1月 - 反对派社会民主党人的伊沃·乔西波维奇（Ivo Josipovic）赢得了总统大选。"
        },
        {
            "type": "paragraph",
            "content": "2010年6月 - 斯洛文尼亚在全民投票中投票支持边境争端国际仲裁。"
        },
        {
            "type": "paragraph",
            "content": "2010年7月 - 乔西波维奇总统访问贝尔格莱德信号与塞尔维亚的关系解冻。"
        },
        {
            "type": "paragraph",
            "content": "2010年11月 - 萨格勒布法院于2010年10月判处六名男子黑手党风格的调查记者伊沃·普卡尼克（Ivo Pukanic）。"
        },
        {
            "type": "paragraph",
            "content": "在克罗地亚与塞尔维亚之间的和解的重要行为中，塞尔维亚总统鲍里斯·塔迪奇（Boris Tadic）访问了维科瓦（Vukovar），他对1991年塞尔维亚部队的260名克罗地亚平民大屠杀道歉。"
        },
        {
            "type": "paragraph",
            "content": "2011年april-两名高级克罗地亚将军 - 安特·戈多维纳（Ante Gotovina）和姆拉登·马尔卡克（Mladen Markac） - 在1995年因对海牙的联合国战争罪行法庭而被定罪。"
        },
        {
            "type": "paragraph",
            "content": "2011年可能 - 克罗地亚和斯洛文尼亚正式提交其皮兰湾边境争端以联合国仲裁。"
        },
        {
            "type": "paragraph",
            "content": "2011年6月 - 克罗地亚成功完成了欧盟加入谈判，这使它在2013年中期成为第28个成员国。"
        },
        {
            "type": "paragraph",
            "content": "2011年7月 - 克罗地亚1991年至1995年内战期间塞尔维亚叛军部队的指挥官戈兰·哈兹奇（Goran Hadzic）在海牙（Hague）对战争罪罪进行审判。"
        },
        {
            "type": "paragraph",
            "content": "2011年11月 - 萨格勒布（Zagreb）开始对腐败指控的伊沃·萨纳德（Ivo Sanader）审判。萨纳德先生否认对他的指控。"
        },
        {
            "type": "paragraph",
            "content": "2011年12月 - 议会选举。由社会民主党人领导的左翼反对派集团罢免了克罗地亚民主联盟（HDZ），该联盟自2003年以来一直掌权。"
        },
        {
            "type": "paragraph",
            "content": "克罗地亚签署了欧盟加入条约，为其在2013年7月获得正式会员铺平了道路。"
        },
        {
            "type": "paragraph",
            "content": "2012年1月 - 克罗地亚选民在全民投票中加入欧盟的一胜率为一对一，尽管低投票率约为44％。"
        },
        {
            "type": "paragraph",
            "content": "2012年6月 - 塞尔维亚法院在1991年在东部洛瓦斯村庄杀害70名克罗地亚平民的14名前士兵和准军事人员。"
        },
        {
            "type": "paragraph",
            "content": "2012年11月 - 安特·戈多维纳将军和姆拉登·马尔卡克（Mladen Markac）对战争罪的定罪被海牙的上诉法院推翻。"
        },
        {
            "type": "paragraph",
            "content": "克罗地亚的法院因贿赂而判处前总理伊沃·萨纳德（Ivo Sanader）入狱10年。"
        },
        {
            "type": "paragraph",
            "content": "2013年3月 - 欧盟委员会给克罗地亚加入欧盟，但表示仍需要解决腐败和有组织犯罪。"
        },
        {
            "type": "paragraph",
            "content": "2013APRIL-克罗地亚在7月1日加入欧盟之前，选举其第一批欧洲议会议员。"
        },
        {
            "type": "paragraph",
            "content": "2013年7月 - 克罗地亚成为欧盟第28位成员。"
        },
        {
            "type": "paragraph",
            "content": "2014年1月 - 欧盟财政部长发起了诉讼，迫使克罗地亚将其预算赤字减半，并将其置于集团允许的限制之下。"
        },
        {
            "type": "paragraph",
            "content": "2014年3月 - 克罗地亚法院因偷窃数百万美元的国家货币而被判入狱9年，以他的第二次腐败定罪。他以前的理事和现任反对派克罗地亚民主联盟（HDZ）党也被判有罪。"
        },
        {
            "type": "paragraph",
            "content": "2014APRIL-克罗地亚特会前南斯拉夫间谍首席Zdravko穆斯塔克（Zdravko Mustac）前往德国，在那里他面临1983年杀害持不同政见者的指控。"
        },
        {
            "type": "paragraph",
            "content": "2015年1月 - 温和的保守派Kolinda Grabar -Kitarovic是克罗地亚的第一任女总统。"
        },
        {
            "type": "paragraph",
            "content": "2015年5月 - 议会通过了一项法律，以补偿1990年代独立战争期间性暴力受害者。"
        },
        {
            "type": "paragraph",
            "content": "2015年11月 - 大选未能获得彻底的赢家。在旷日持久的会谈之后，非党派的技术官僚Tihomir Oreskovic于2016年1月成为总理。"
        },
        {
            "type": "paragraph",
            "content": "2016年6月 - 政府在奥雷斯科维奇（Oreskovic）及其内阁未能在主要联盟伙伴之间发生争吵之后未能赢得信任投票。"
        },
        {
            "type": "paragraph",
            "content": "2016年7月 - 议会被解散，新的选举被要求为9月。"
        },
        {
            "type": "paragraph",
            "content": "2016年9月 - 举行选举，中右民族主义者克罗地亚民主联盟（HDZ）党赢得了最多的席位。"
        },
        {
            "type": "paragraph",
            "content": "2016年10月 - 由HDZ领导人安德烈·普伦科维奇（Andrej Plenkovic）领导的中右联盟政府就职。"
        },
        {
            "type": "paragraph",
            "content": "2017年9月 - 前准军事指挥官德拉曼·瓦西尔·科维奇（Dragan Vasiljkovic）被判犯有战争罪行，并因在1990年代初期的冲突中折磨和杀害囚犯而被判入狱。"
        },
        {
            "type": "paragraph",
            "content": "2020年7月 - 安德烈·普伦科维奇（Andrej Plenkovic）赢得了总理的第二任期。"
        }
    ]
}